pqdpy/__init__.py
pqdpy/auxiliary.py
pqdpy/synthetic.py
pqdpy-0.1.0.dist-info/LICENSE
pqdpy-0.1.0.dist-info/METADATA
pqdpy-0.1.0.dist-info/WHEEL
pqdpy-0.1.0.dist-info/RECORD
