Metadata-Version: 2.1
Name: pqdpy
Version: 0.1.0
Summary: Power quality disturbances dataset generator
License: GNU General Public License v3.0
Author: Rafael Angel Montoya Gutierrez
Requires-Python: >=3.9
Classifier: License :: Other/Proprietary License
Classifier: Programming Language :: Python :: 3
Classifier: Programming Language :: Python :: 3.9
Classifier: Programming Language :: Python :: 3.10
Classifier: Programming Language :: Python :: 3.11
Requires-Dist: matplotlib (>=3.8.3)
Requires-Dist: numpy (>=1.26.4)
Requires-Dist: pandas (>=2.2.1)
